h5ify/__init__.py
h5ify/h5ify.py
h5ify-0.2.3.dist-info/LICENSE
h5ify-0.2.3.dist-info/METADATA
h5ify-0.2.3.dist-info/WHEEL
h5ify-0.2.3.dist-info/top_level.txt
h5ify-0.2.3.dist-info/RECORD
