Metadata-Version: 2.2
Name: h5ify
Version: 0.2.3
Summary: Save Python dictionaries into HDF5 files; load HDF5 files into Python dictionaries.
Author-email: Matthew Mould <mattdmould@gmail.com>
Project-URL: Homepage, https://github.com/mdmould/h5ify
Classifier: Programming Language :: Python :: 3
Classifier: License :: OSI Approved :: MIT License
Classifier: Operating System :: OS Independent
Requires-Python: >=3.9
License-File: LICENSE
Requires-Dist: h5py
